gradio_annotatedaudio/__init__.py
gradio_annotatedaudio/annotatedaudio.py
gradio_annotatedaudio/annotatedaudio.pyi
gradio_annotatedaudio/core.py
gradio_annotatedaudio/templates/component/__vite-browser-external-2447137e.js
gradio_annotatedaudio/templates/component/index.js
gradio_annotatedaudio/templates/component/module-2c3384e6.js
gradio_annotatedaudio/templates/component/module-aafe8b06.js
gradio_annotatedaudio/templates/component/module-d82531d9.js
gradio_annotatedaudio/templates/component/style.css
gradio_annotatedaudio/templates/component/wrapper-6f348d45-19fa94bf.js
gradio_annotatedaudio/templates/example/index.js
gradio_annotatedaudio/templates/example/style.css
gradio_annotatedaudio-0.1.3.dist-info/METADATA
gradio_annotatedaudio-0.1.3.dist-info/WHEEL
gradio_annotatedaudio-0.1.3.dist-info/RECORD
